mtenv/__init__.py
mtenv/command.py
mtenv666-0.0.1.dist-info/LICENSE
mtenv666-0.0.1.dist-info/METADATA
mtenv666-0.0.1.dist-info/WHEEL
mtenv666-0.0.1.dist-info/entry_points.txt
mtenv666-0.0.1.dist-info/top_level.txt
mtenv666-0.0.1.dist-info/zip-safe
mtenv666-0.0.1.dist-info/RECORD
