Metadata-Version: 2.1
Name: mtenv666
Version: 0.0.1
Summary: 环境参数
Author: ziyu
Author-email: 3491360008@qq.com
License: MIT
Keywords: quant,finance
Classifier: License :: OSI Approved :: MIT License
Classifier: Programming Language :: Python
Classifier: Intended Audience :: Developers
Classifier: Operating System :: OS Independent
License-File: LICENSE
